{"format_version":"1.12.0","minecraft:geometry":[{"description":{"identifier":"geometry.hive.murder.gravestone.pirates.fate","texture_width":75,"texture_height":75,"visible_bounds_width":4,"visible_bounds_height":2.5,"visible_bounds_offset":[0,0.75,0]},"bones":[{"name":"root","pivot":[0,0,0]},{"name":"gravestone","parent":"root","pivot":[0,0,0],"cubes":[{"origin":[-5,0,3],"size":[10,13,2],"pivot":[0,0,3],"rotation":[-2.5,12.5,0],"uv":[37,19]},{"origin":[-6,0.1,-6],"size":[12,0,10],"uv":[14,34]}]},{"name":"hat","parent":"gravestone","pivot":[2,12,4],"rotation":[-12.45392,1.08089,19.88206],"cubes":[{"origin":[-2,12,0],"size":[8,4,8],"uv":[40,0]},{"origin":[-5,12,-2],"size":[14,6,12],"uv":[0,0]}]},{"name":"skull","parent":"gravestone","pivot":[-3,0,-6],"rotation":[-17.5,-20,0],"cubes":[{"origin":[-7,2,-8],"size":[8,6,8],"uv":[0,19]},{"origin":[-6,8,-7],"size":[6,1,6],"uv":[0,33]},{"origin":[-5,0,-8],"size":[4,2,2],"uv":[25,22]}]},{"name":"rightEyeBrow","parent":"skull","pivot":[-5.4,5.3,-7.7],"cubes":[{"origin":[-6.95,4.8,-8.01],"size":[4,1,0],"pivot":[-5.4,5.3,-7.7],"rotation":[0,0,7.5],"uv":[0,22],"mirror":true}]},{"name":"leftEyeBrow","parent":"skull","pivot":[-0.6,5.3,-7.7],"cubes":[{"origin":[-3.05,4.8,-8.01],"size":[4,1,0],"pivot":[-0.6,5.3,-7.7],"rotation":[0,0,-7.5],"uv":[0,22]}]}]}]}