{"format_version":"1.12.0","minecraft:geometry":[{"description":{"identifier":"geometry.hive.murder.prop.manor.bookcase.2","texture_width":120,"texture_height":98,"visible_bounds_width":4,"visible_bounds_height":8,"visible_bounds_offset":[0,1,0]},"bones":[{"name":"root","pivot":[-16,0,0],"cubes":[{"origin":[-24,0,-4],"size":[48,64,12],"uv":[0,0]},{"origin":[-24,0,-8],"size":[48,4,4],"uv":[0,77]},{"origin":[-24,60,-8],"size":[48,4,4],"uv":[0,77]},{"origin":[-24,45,-8],"size":[48,4,4],"uv":[0,77]},{"origin":[-24,15,-8],"size":[48,4,4],"uv":[0,77]},{"origin":[-24,30,-8],"size":[48,4,4],"uv":[0,77]},{"origin":[1,34,-7],"size":[3,9,3],"uv":[13,85]},{"origin":[-20,19,-7],"size":[8,3,3],"uv":[37,86]},{"origin":[-5,49,-7],"size":[3,7,3],"uv":[79,86]},{"origin":[3,4,-6],"size":[3,7,3],"uv":[79,86]},{"origin":[11.5,49,-6],"size":[3,7,2],"pivot":[11.5,49,-5],"rotation":[0,0,-12.5],"uv":[26,86]},{"origin":[11,34,-6],"size":[4,10,2],"uv":[0,85]},{"origin":[14,4,-7],"size":[3,9,3],"uv":[92,86]},{"origin":[-3,19,-7],"size":[6,6,3],"pivot":[3,19,-4],"rotation":[0,10,0],"uv":[60,86]},{"origin":[-2,26,-6],"size":[4,2,2],"pivot":[3,19,-4],"rotation":[0,10,0],"uv":[37,92]},{"origin":[-1,25,-5],"size":[2,1,1],"pivot":[3,19,-4],"rotation":[0,10,0],"uv":[70,86]}]}]}]}