{
  "format_version": "1.12.0",
  "minecraft:geometry": [
    {
      "bones": [
        {
          "cubes": [
            {
              "origin": [
                -8,
                9.5,
                -1
              ],
              "size": [
                8,
                3,
                1
              ],
              "uv": {
                "down": {
                  "uv": [
                    6,
                    6
                  ],
                  "uv_size": [
                    8,
                    1
                  ]
                },
                "east": {
                  "uv": [
                    13,
                    0
                  ],
                  "uv_size": [
                    1,
                    3
                  ]
                },
                "north": {
                  "uv": [
                    6,
                    4
                  ],
                  "uv_size": [
                    8,
                    3
                  ]
                },
                "south": {
                  "uv": [
                    6,
                    0
                  ],
                  "uv_size": [
                    8,
                    3
                  ]
                },
                "up": {
                  "uv": [
                    14,
                    5
                  ],
                  "uv_size": [
                    -8,
                    -1
                  ]
                },
                "west": {
                  "uv": [
                    13,
                    0
                  ],
                  "uv_size": [
                    1,
                    3
                  ]
                }
              }
            },
            {
              "origin": [
                -8,
                3.5,
                -1
              ],
              "size": [
                8,
                3,
                1
              ],
              "uv": {
                "down": {
                  "uv": [
                    6,
                    6
                  ],
                  "uv_size": [
                    8,
                    1
                  ]
                },
                "east": {
                  "uv": [
                    13,
                    0
                  ],
                  "uv_size": [
                    1,
                    3
                  ]
                },
                "north": {
                  "uv": [
                    6,
                    4
                  ],
                  "uv_size": [
                    8,
                    3
                  ]
                },
                "south": {
                  "uv": [
                    6,
                    0
                  ],
                  "uv_size": [
                    8,
                    3
                  ]
                },
                "up": {
                  "uv": [
                    14,
                    5
                  ],
                  "uv_size": [
                    -8,
                    -1
                  ]
                },
                "west": {
                  "uv": [
                    13,
                    0
                  ],
                  "uv_size": [
                    1,
                    3
                  ]
                }
              }
            },
            {
              "origin": [
                -6,
                0,
                0
              ],
              "size": [
                4,
                16,
                1
              ],
              "uv": {
                "down": {
                  "uv": [
                    0,
                    16
                  ],
                  "uv_size": [
                    4,
                    -1
                  ]
                },
                "east": {
                  "uv": [
                    1,
                    0
                  ],
                  "uv_size": [
                    -1,
                    16
                  ]
                },
                "north": {
                  "uv": [
                    4,
                    0
                  ],
                  "uv_size": [
                    -4,
                    16
                  ]
                },
                "south": {
                  "uv": [
                    4,
                    0
                  ],
                  "uv_size": [
                    -4,
                    16
                  ]
                },
                "up": {
                  "uv": [
                    0,
                    0
                  ],
                  "uv_size": [
                    4,
                    1
                  ]
                },
                "west": {
                  "uv": [
                    4,
                    0
                  ],
                  "uv_size": [
                    -1,
                    16
                  ]
                }
              }
            },
            {
              "origin": [
                -3.5,
                9.5,
                -1
              ],
              "pivot": [
                -1.75,
                8,
                -1.75
              ],
              "rotation": [
                0,
                90,
                0
              ],
              "size": [
                8,
                3,
                1
              ],
              "uv": {
                "down": {
                  "uv": [
                    6,
                    6
                  ],
                  "uv_size": [
                    8,
                    1
                  ]
                },
                "east": {
                  "uv": [
                    13,
                    0
                  ],
                  "uv_size": [
                    1,
                    3
                  ]
                },
                "north": {
                  "uv": [
                    6,
                    4
                  ],
                  "uv_size": [
                    8,
                    3
                  ]
                },
                "south": {
                  "uv": [
                    6,
                    0
                  ],
                  "uv_size": [
                    8,
                    3
                  ]
                },
                "up": {
                  "uv": [
                    14,
                    5
                  ],
                  "uv_size": [
                    -8,
                    -1
                  ]
                },
                "west": {
                  "uv": [
                    13,
                    0
                  ],
                  "uv_size": [
                    1,
                    3
                  ]
                }
              }
            },
            {
              "origin": [
                -3.5,
                3.5,
                -1
              ],
              "pivot": [
                -1.75,
                8,
                -1.75
              ],
              "rotation": [
                0,
                90,
                0
              ],
              "size": [
                8,
                3,
                1
              ],
              "uv": {
                "down": {
                  "uv": [
                    6,
                    6
                  ],
                  "uv_size": [
                    8,
                    1
                  ]
                },
                "east": {
                  "uv": [
                    13,
                    0
                  ],
                  "uv_size": [
                    1,
                    3
                  ]
                },
                "north": {
                  "uv": [
                    6,
                    4
                  ],
                  "uv_size": [
                    8,
                    3
                  ]
                },
                "south": {
                  "uv": [
                    6,
                    0
                  ],
                  "uv_size": [
                    8,
                    3
                  ]
                },
                "up": {
                  "uv": [
                    14,
                    5
                  ],
                  "uv_size": [
                    -8,
                    -1
                  ]
                },
                "west": {
                  "uv": [
                    13,
                    0
                  ],
                  "uv_size": [
                    1,
                    3
                  ]
                }
              }
            },
            {
              "origin": [
                -1.5,
                0,
                0
              ],
              "pivot": [
                -1.75,
                8,
                -1.75
              ],
              "rotation": [
                0,
                90,
                0
              ],
              "size": [
                4,
                16,
                1
              ],
              "uv": {
                "down": {
                  "uv": [
                    0,
                    16
                  ],
                  "uv_size": [
                    4,
                    -1
                  ]
                },
                "east": {
                  "uv": [
                    1,
                    0
                  ],
                  "uv_size": [
                    -1,
                    16
                  ]
                },
                "north": {
                  "uv": [
                    4,
                    0
                  ],
                  "uv_size": [
                    -4,
                    16
                  ]
                },
                "south": {
                  "uv": [
                    4,
                    0
                  ],
                  "uv_size": [
                    -4,
                    16
                  ]
                },
                "up": {
                  "uv": [
                    0,
                    0
                  ],
                  "uv_size": [
                    4,
                    1
                  ]
                },
                "west": {
                  "uv": [
                    4,
                    0
                  ],
                  "uv_size": [
                    -1,
                    16
                  ]
                }
              }
            }
          ],
          "name": "root",
          "pivot": [
            -1.75,
            8,
            -1.75
          ]
        }
      ],
      "description": {
        "identifier": "geometry.hive.block.picket.fence.corner",
        "texture_height": 16,
        "texture_width": 16,
        "visible_bounds_height": 3.5,
        "visible_bounds_offset": [
          0,
          1.25,
          0
        ],
        "visible_bounds_width": 4
      }
    }
  ]
}
