{"format_version":"1.10.0","minecraft:client_entity":{"description":{"identifier":"hivehub:mailbot","materials":{"default":"entity_alphatest","blend":"slime_outer"},"textures":{"default":"textures/entity/hive/hub/mailbot"},"geometry":{"default":"geometry.hive.hub.mailbot"},"animations":{"controller_idle":"controller.animation.hive.hub.mailbot.idle","controller_action":"controller.animation.hive.hub.mailbot.action","idle":"animation.hive.hub.mailbot.idle","idle_face":"animation.hive.hub.mailbot.idle.face","idle_blink":"animation.hive.hub.mailbot.idle.blink","package":"animation.hive.hub.mailbot.package","pipe":"animation.hive.hub.mailbot.pipe","laptop":"animation.hive.hub.mailbot.laptop"},"scripts":{"initialize":["variable.show_package_assets \u003d 0;","variable.show_pipe_assets \u003d 0;","variable.resume_idle \u003d 0;"],"animate":["controller_idle","controller_action"]},"render_controllers":["controller.render.hive.hub.mailbot"]}}}